Workbook

Sheet Resumo
A1: Confissão de Dívida - Cemil Tubos e Conexões
A2: Ao valor confessado, serão incorporados mensalmente correção monetária com base na Taxa SELIC (aplicados sobre o valor da dívida ativa)
A3: Saldo inicial (original) | B3: 2983673
A4: Abatimento Tecnomonte (amortização) | B4: -172364.3
A5: Valor parcela | B5: =Parâmetros!B5 -> 20000
A6: Total pago (Parcelas semanais de R$20.000,00 pagas até 19/09/2025) | B6: =-32*Parâmetros!B5 -> -640000
A7: Saldo Atual | B7: =SUM(B3+B4+B6) -> 2171308.7
A8: Observação: | B8: O nº de parcelas extras depende da SELIC lançada mês a mês.

Sheet Parâmetros
A1: Parâmetros do Acordo
A3: Saldo inicial (data base) | B3: 2171308.7
A4: Data base (início) | B4: 45926
A5: Valor parcela (fixa) | B5: 20000
A7: Tabela SELIC (mensal)
A8: Competência (AAAA-MM) | B8: Taxa Mensal (%)
A9: 2025-08 | B9: 0.0116
A10: 2025-09 | B10: 0.0122
A11: 2025-10 | B11: 0.0128
A12: 2025-11 | B12: 0.0105
A13: 2025-12 | B13: 0.0122
A14: 2026-01 | B14: 0.0116
A15: 2026-02 | B15: 0.0116
A16: 2026-03 | B16: 0
A17: 2026-04 | B17: 0
A18: 2026-05 | B18: 0
A19: 2026-06 | B19: 0
A20: 2026-07 | B20: 0
... A25: 2026-12 | B25: 0

Sheet Modelo B
A1: Resumo do Acordo – Confissão de Dívida
A2: Valor da dívida (base) | B2: =Parâmetros!B3 -> 2171308.7 | E2: Valor da parcela | F2: =Parâmetros!B5 -> 20000
A3: *Se cair em feriado, antecipar manualmente a data para o dia útil anterior.
A5: Parcela # | B5: Data prevista | C5: Dia da semana | D5: Valor parcela | E5: Data pagamento | F5: Valor pago | G5: Saldo anterior | H5: Juros (Selic mês) | I5: Amortização | J5: Saldo após pagamento | K5: Observações
A6: 28 | B6: 45891 | C6: Friday | D6: =Parâmetros!B5 -> 20000 | E6: 45891 | F6: =D6 -> 20000 | G6: =$B$2 -> 2171308.7 | I6: =MIN(D6,G6) -> 20000 | J6: =G6-I6+H6 -> 2151308.7
A7: 29 | B7: 45898 | C7: Friday | D7: =Parâmetros!B5 -> 20000 | E7: 45898 | F7: =D7 -> 20000 | G7: =J6 -> 2151308.7 | I7: =MIN(D7,G7) -> 20000 | J7: =G7-I7+H7 -> 2131308.7
A8: 30 | B8: 45905 | C8: Friday | D8: =Parâmetros!B5 -> 20000 | E8: 45905 | F8: =D8 -> 20000 | G8: =J7 -> 2131308.7 | I8: =MIN(D8,G8) -> 20000 | J8: =G8-I8+H8 -> 2111308.7
A9: 31 | B9: 45912 | C9: Friday | D9: =Parâmetros!B5 -> 20000 | E9: 45912 | F9: =D9 -> 20000 | G9: =J8 -> 2111308.7 | I9: =MIN(D9,G9) -> 20000 | J9: =G9-I9+H9 -> 2091308.7
A10: 32 | B10: 45919 | C10: Friday | D10: =Parâmetros!B5 -> 20000 | E10: 45919 | F10: =D10 -> 20000 | G10: =J9 -> 2091308.7 | I10: =MIN(D10,G10) -> 20000 | J10: =G10-I10+H10 -> 2071308.7
A11: 33 | B11: 45926 | C11: Friday | D11: =Parâmetros!B5 -> 20000 | E11: 45926 | F11: 20000 | G11: =J10 -> 2071308.7 | I11: =MIN(D11,G11) -> 20000 | J11: =G11-I11+H11 -> 2051308.7
A12: 34 | B12: 45929 | C12: Monday | D12: =Parâmetros!B5 -> 20000 | G12: =J11 -> 2051308.7 | H12: 0.0122 | I12: =MIN(D12,G12) -> 20000 | J12: =G12-I12+H12 -> 2031308.7
A13: 35 | B13: 45933 | C13: Friday | D13: =Parâmetros!B5 -> 20000 | G13: =J12 -> 2031308.7 | I13: =MIN(D13,G13) -> 20000 | J13: =SUM(G13-I13)*H13+(G13-I13) -> 2011308.7
A14: 36 | B14: 45936 | C14: Monday | D14: =Parâmetros!B5 -> 20000 | G14: =J13 -> 2011308.7 | I14: =MIN(D14,G14) -> 20000 | J14: =SUM(G14-I14)*H14+(G14-I14) -> 1991308.7
A15: 37 | B15: 45940 | C15: Friday | D15: =Parâmetros!B5 -> 20000 | G15: =J14 -> 1991308.7 | I15: =MIN(D15,G15) -> 20000 | J15: =SUM(G15-I15)*H15+(G15-I15) -> 1971308.7
A16: 38 | B16: 45943 | C16: Monday | D16: =Parâmetros!B5 -> 20000 | G16: =J15 -> 1971308.7 | I16: =MIN(D16,G16) -> 20000 | J16: =SUM(G16-I16)*H16+(G16-I16) -> 1951308.7
A17: 39 | B17: 45947 | C17: Friday | D17: =Parâmetros!B5 -> 20000 | G17: =J16 -> 1951308.7 | I17: =MIN(D17,G17) -> 20000 | J17: =SUM(G17-I17)*H17+(G17-I17) -> 1931308.7
A18: 40 | B18: 45950 | C18: Monday | D18: =Parâmetros!B5 -> 20000 | G18: =J17 -> 1931308.7 | I18: =MIN(D18,G18) -> 20000 | J18: =SUM(G18-I18)*H18+(G18-I18) -> 1911308.7
A19: 41 | B19: 45954 | C19: Friday | D19: =Parâmetros!B5 -> 20000 | G19: =J18 -> 1911308.7 | I19: =MIN(D19,G19) -> 20000 | J19: =SUM(G19-I19)*H19+(G19-I19) -> 1891308.7
A20: 42 | B20: 45957 | C20: Monday | D20: =Parâmetros!B5 -> 20000 | G20: =J19 -> 1891308.7 | I20: =MIN(D20,G20) -> 20000 | J20: =SUM(G20-I20)*H20+(G20-I20) -> 1871308.7
A21: 43 | B21: 45961 | C21: Friday | D21: =Parâmetros!B5 -> 20000 | G21: =J20 -> 1871308.7 | H21: 0.0128 | I21: =MIN(D21,G21) -> 20000 | J21: =SUM(G21-I21)*H21+(G21-I21) -> 1875005.4
A22: 44 | B22: 45964 | C22: Monday | D22: =Parâmetros!B5 -> 20000 | G22: =J21 -> 1875005.4 | I22: =MIN(D22,G22) -> 20000 | J22: =SUM(G22-I22)*H22+(G22-I22) -> 1855005.4
A23: 45 | B23: 45968 | C23: Friday | D23: =Parâmetros!B5 -> 20000 | G23: =J22 -> 1855005.4 | I23: =MIN(D23,G23) -> 20000 | J23: =SUM(G23-I23)*H23+(G23-I23) -> 1835005.4
A24: 46 | B24: 45971 | C24: Monday | D24: =Parâmetros!B5 -> 20000 | G24: =J23 -> 1835005.4 | I24: =MIN(D24,G24) -> 20000 | J24: =SUM(G24-I24)*H24+(G24-I24) -> 1815005.4
A25: 47 | B25: 45975 | C25: Friday | D25: =Parâmetros!B5 -> 20000 | G25: =J24 -> 1815005.4 | I25: =MIN(D25,G25) -> 20000 | J25: =SUM(G25-I25)*H25+(G25-I25) -> 1795005.4
A26: 48 | B26: 45978 | C26: Monday | D26: =Parâmetros!B5 -> 20000 | G26: =J25 -> 1795005.4 | I26: =MIN(D26,G26) -> 20000 | J26: =SUM(G26-I26)*H26+(G26-I26) -> 1775005.4
A27: 49 | B27: 45982 | C27: Friday | D27: =Parâmetros!B5 -> 20000 | G27: =J26 -> 1775005.4 | I27: =MIN(D27,G27) -> 20000 | J27: =SUM(G27-I27)*H27+(G27-I27) -> 1755005.4
A28: 50 | B28: 45985 | C28: Monday | D28: =Parâmetros!B5 -> 20000 | G28: =J27 -> 1755005.4 | I28: =MIN(D28,G28) -> 20000 | J28: =SUM(G28-I28)*H28+(G28-I28) -> 1735005.4
A29: 51 | B29: 45989 | C29: Friday | D29: =Parâmetros!B5 -> 20000 | G29: =J28 -> 1735005.4 | H29: 0.0105 | I29: =MIN(D29,G29) -> 20000 | J29: =SUM(G29-I29)*H29+(G29-I29) -> 1733013
A30: 52 | B30: 45992 | C30: Monday | D30: =Parâmetros!B5 -> 20000 | G30: =J29 -> 1733013 | I30: =MIN(D30,G30) -> 20000 | J30: =SUM(G30-I30)*H30+(G30-I30) -> 1713013
A31: 53 | B31: 45996 | C31: Friday | D31: =Parâmetros!B5 -> 20000 | G31: =J30 -> 1713013 | I31: =MIN(D31,G31) -> 20000 | J31: =SUM(G31-I31)*H31+(G31-I31) -> 1693013
A32: 54 | B32: 45999 | C32: Monday | D32: =Parâmetros!B5 -> 20000 | G32: =J31 -> 1693013 | I32: =MIN(D32,G32) -> 20000 | J32: =SUM(G32-I32)*H32+(G32-I32) -> 1673013
A33: 55 | B33: 46003 | C33: Friday | D33: =Parâmetros!B5 -> 20000 | G33: =J32 -> 1673013 | I33: =MIN(D33,G33) -> 20000 | J33: =SUM(G33-I33)*H33+(G33-I33) -> 1653013
A34: 56 | B34: 46006 | C34: Monday | D34: =Parâmetros!B5 -> 20000 | G34: =J33 -> 1653013 | I34: =MIN(D34,G34) -> 20000 | J34: =SUM(G34-I34)*H34+(G34-I34) -> 1633013
A35: 57 | B35: 46010 | C35: Friday | D35: =Parâmetros!B5 -> 20000 | G35: =J34 -> 1633013 | I35: =MIN(D35,G35) -> 20000 | J35: =SUM(G35-I35)*H35+(G35-I35) -> 1613013
A36: 58 | B36: 46013 | C36: Monday | D36: =Parâmetros!B5 -> 20000 | G36: =J35 -> 1613013 | I36: =MIN(D36,G36) -> 20000 | J36: =SUM(G36-I36)*H36+(G36-I36) -> 1593013
A37: 59 | B37: 46017 | C37: Friday | D37: =Parâmetros!B5 -> 20000 | G37: =J36 -> 1593013 | I37: =MIN(D37,G37) -> 20000 | J37: =SUM(G37-I37)*H37+(G37-I37) -> 1573013
A38: 60 | B38: 46020 | C38: Monday | D38: =Parâmetros!B5 -> 20000 | G38: =J37 -> 1573013 | H38: 0.0122 | I38: =MIN(D38,G38) -> 20000 | J38: =SUM(G38-I38)*H38+(G38-I38) -> 1571959.7
A39: 61 | B39: 46024 | C39: Friday | D39: =Parâmetros!B5 -> 20000 | G39: =J38 -> 1571959.7 | I39: =MIN(D39,G39) -> 20000 | J39: =SUM(G39-I39)*H39+(G39-I39) -> 1551959.7
A40: 62 | B40: 46027 | C40: Monday | D40: =Parâmetros!B5 -> 20000 | G40: =J39 -> 1551959.7 | I40: =MIN(D40,G40) -> 20000 | J40: =SUM(G40-I40)*H40+(G40-I40) -> 1531959.7
A41: 63 | B41: 46031 | C41: Friday | D41: =Parâmetros!B5 -> 20000 | G41: =J40 -> 1531959.7 | I41: =MIN(D41,G41) -> 20000 | J41: =SUM(G41-I41)*H41+(G41-I41) -> 1511959.7
A42: 64 | B42: 46034 | C42: Monday | D42: =Parâmetros!B5 -> 20000 | G42: =J41 -> 1511959.7 | I42: =MIN(D42,G42) -> 20000 | J42: =SUM(G42-I42)*H42+(G42-I42) -> 1491959.7
A43: 65 | B43: 46038 | C43: Friday | D43: =Parâmetros!B5 -> 20000 | G43: =J42 -> 1491959.7 | I43: =MIN(D43,G43) -> 20000 | J43: =SUM(G43-I43)*H43+(G43-I43) -> 1471959.7
A44: 66 | B44: 46041 | C44: Monday | D44: =Parâmetros!B5 -> 20000 | G44: =J43 -> 1471959.7 | I44: =MIN(D44,G44) -> 20000 | J44: =SUM(G44-I44)*H44+(G44-I44) -> 1451959.7
A45: 67 | B45: 46045 | C45: Friday | D45: =Parâmetros!B5 -> 20000 | G45: =J44 -> 1451959.7 | I45: =MIN(D45,G45) -> 20000 | J45: =SUM(G45-I45)*H45+(G45-I45) -> 1431959.7
A46: 68 | B46: 46048 | C46: Monday | D46: =Parâmetros!B5 -> 20000 | G46: =J45 -> 1431959.7 | I46: =MIN(D46,G46) -> 20000 | J46: =SUM(G46-I46)*H46+(G46-I46) -> 1411959.7
A47: 69 | B47: 46052 | C47: Friday | D47: =Parâmetros!B5 -> 20000 | G47: =J46 -> 1411959.7 | H47: 0.0116 | I47: =MIN(D47,G47) -> 20000 | J47: =SUM(G47-I47)*H47+(G47-I47) -> 1408106.5
A48: 70 | B48: 46055 | C48: Monday | D48: =Parâmetros!B5 -> 20000 | G48: =J47 -> 1408106.5 | I48: =MIN(D48,G48) -> 20000 | J48: =SUM(G48-I48)*H48+(G48-I48) -> 1388106.5
A49: 71 | B49: 46059 | C49: Friday | D49: =Parâmetros!B5 -> 20000 | G49: =J48 -> 1388106.5 | I49: =MIN(D49,G49) -> 20000 | J49: =SUM(G49-I49)*H49+(G49-I49) -> 1368106.5
A50: 72 | B50: 46062 | C50: Monday | D50: =Parâmetros!B5 -> 20000 | G50: =J49 -> 1368106.5 | I50: =MIN(D50,G50) -> 20000 | J50: =SUM(G50-I50)*H50+(G50-I50) -> 1348106.5
A51: 73 | B51: 46066 | C51: Friday | D51: =Parâmetros!B5 -> 20000 | G51: =J50 -> 1348106.5 | I51: =MIN(D51,G51) -> 20000 | J51: =SUM(G51-I51)*H51+(G51-I51) -> 1328106.5
A52: 74 | B52: 46069 | C52: Monday | D52: =Parâmetros!B5 -> 20000 | G52: =J51 -> 1328106.5 | I52: =MIN(D52,G52) -> 20000 | J52: =SUM(G52-I52)*H52+(G52-I52) -> 1308106.5
A53: 75 | B53: 46073 | C53: Friday | D53: =Parâmetros!B5 -> 20000 | G53: =J52 -> 1308106.5 | I53: =MIN(D53,G53) -> 20000 | J53: =SUM(G53-I53)*H53+(G53-I53) -> 1288106.5
A54: 76 | B54: 46076 | C54: Monday | D54: =Parâmetros!B5 -> 20000 | G54: =J53 -> 1288106.5 | I54: =MIN(D54,G54) -> 20000 | J54: =SUM(G54-I54)*H54+(G54-I54) -> 1268106.5
A55: 77 | B55: 46080 | C55: Friday | D55: =Parâmetros!B5 -> 20000 | G55: =J54 -> 1268106.5 | H55: 0.0115 | I55: =MIN(D55,G55) -> 20000 | J55: =SUM(G55-I55)*H55+(G55-I55) -> 1262459.7
A56: 78 | B56: 46083 | C56: Monday | D56: =Parâmetros!B5 -> 20000 | G56: =J55 -> 1262459.7 | I56: =MIN(D56,G56) -> 20000 | J56: =SUM(G56-I56)*H56+(G56-I56) -> 1242459.7
A57: 79 | B57: 46087 | C57: Friday | D57: =Parâmetros!B5 -> 20000 | G57: =J56 -> 1242459.7 | I57: =MIN(D57,G57) -> 20000 | J57: =SUM(G57-I57)*H57+(G57-I57) -> 1222459.7
A58: 80 | B58: 46090 | C58: Monday | D58: =Parâmetros!B5 -> 20000 | G58: =J57 -> 1222459.7 | I58: =MIN(D58,G58) -> 20000 | J58: =SUM(G58-I58)*H58+(G58-I58) -> 1202459.7
A59: 81 | B59: 46094 | C59: Friday | D59: =Parâmetros!B5 -> 20000 | G59: =J58 -> 1202459.7 | I59: =MIN(D59,G59) -> 20000 | J59: =SUM(G59-I59)*H59+(G59-I59) -> 1182459.7
A60: 82 | B60: 46097 | C60: Monday | D60: =Parâmetros!B5 -> 20000 | G60: =J59 -> 1182459.7 | I60: =MIN(D60,G60) -> 20000 | J60: =SUM(G60-I60)*H60+(G60-I60) -> 1162459.7
A61: 83 | B61: 46101 | C61: Friday | D61: =Parâmetros!B5 -> 20000 | G61: =J60 -> 1162459.7 | I61: =MIN(D61,G61) -> 20000 | J61: =SUM(G61-I61)*H61+(G61-I61) -> 1142459.7
A62: 84 | B62: 46104 | C62: Monday | D62: =Parâmetros!B5 -> 20000 | G62: =J61 -> 1142459.7 | I62: =MIN(D62,G62) -> 20000 | J62: =SUM(G62-I62)*H62+(G62-I62) -> 1122459.7
A63: 85 | B63: 46108 | C63: Friday | D63: =Parâmetros!B5 -> 20000 | G63: =J62 -> 1122459.7 | I63: =MIN(D63,G63) -> 20000 | J63: =SUM(G63-I63)*H63+(G63-I63) -> 1102459.7
A64: 86 | B64: 46111 | C64: Monday | D64: =Parâmetros!B5 -> 20000 | G64: =J63 -> 1102459.7 | H64: 0.0179 | I64: =MIN(D64,G64) -> 20000 | J64: =SUM(G64-I64)*H64+(G64-I64) -> 1101835.7
A65: 87 | B65: 46115 | C65: Friday | D65: =Parâmetros!B5 -> 20000 | G65: =J64 -> 1101835.7 | I65: =MIN(D65,G65) -> 20000 | J65: =SUM(G65-I65)*H65+(G65-I65) -> 1081835.7
A66: 88 | B66: 46118 | C66: Monday | D66: =Parâmetros!B5 -> 20000 | G66: =J65 -> 1081835.7 | I66: =MIN(D66,G66) -> 20000 | J66: =SUM(G66-I66)*H66+(G66-I66) -> 1061835.7
A67: 89 | B67: 46122 | C67: Friday | D67: =Parâmetros!B5 -> 20000 | G67: =J66 -> 1061835.7 | I67: =MIN(D67,G67) -> 20000 | J67: =SUM(G67-I67)*H67+(G67-I67) -> 1041835.7
A68: 90 | B68: 46125 | C68: Monday | D68: =Parâmetros!B5 -> 20000 | G68: =J67 -> 1041835.7 | I68: =MIN(D68,G68) -> 20000 | J68: =SUM(G68-I68)*H68+(G68-I68) -> 1021835.7
A69: 91 | B69: 46129 | C69: Friday | D69: =Parâmetros!B5 -> 20000 | G69: =J68 -> 1021835.7 | I69: =MIN(D69,G69) -> 20000 | J69: =SUM(G69-I69)*H69+(G69-I69) -> 1001835.7
A70: 92 | B70: 46132 | C70: Monday | D70: =Parâmetros!B5 -> 20000 | G70: =J69 -> 1001835.7 | I70: =MIN(D70,G70) -> 20000 | J70: =SUM(G70-I70)*H70+(G70-I70) -> 981835.74
A71: 93 | B71: 46136 | C71: Friday | D71: =Parâmetros!B5 -> 20000 | G71: =J70 -> 981835.74 | I71: =MIN(D71,G71) -> 20000 | J71: =SUM(G71-I71)*H71+(G71-I71) -> 961835.74
A72: 94 | B72: 46139 | C72: Monday | D72: =Parâmetros!B5 -> 20000 | G72: =J71 -> 961835.74 | H72: 0.0167 | I72: =MIN(D72,G72) -> 20000 | J72: =SUM(G72-I72)*H72+(G72-I72) -> 957564.39
A73: 95 | B73: 46143 | C73: Friday | D73: =Parâmetros!B5 -> 20000 | G73: =J72 -> 957564.39 | I73: =MIN(D73,G73) -> 20000 | J73: =SUM(G73-I73)*H73+(G73-I73) -> 937564.39
A74: 96 | B74: 46146 | C74: Monday | D74: =Parâmetros!B5 -> 20000 | G74: =J73 -> 937564.39 | I74: =MIN(D74,G74) -> 20000 | J74: =SUM(G74-I74)*H74+(G74-I74) -> 917564.39
A75: 97 | B75: 46150 | C75: Friday | D75: =Parâmetros!B5 -> 20000 | G75: =J74 -> 917564.39 | I75: =MIN(D75,G75) -> 20000 | J75: =SUM(G75-I75)*H75+(G75-I75) -> 897564.39
A76: 98 | B76: 46153 | C76: Monday | D76: =Parâmetros!B5 -> 20000 | G76: =J75 -> 897564.39 | I76: =MIN(D76,G76) -> 20000 | J76: =SUM(G76-I76)*H76+(G76-I76) -> 877564.39
A77: 99 | B77: 46157 | C77: Friday | D77: =Parâmetros!B5 -> 20000 | G77: =J76 -> 877564.39 | I77: =MIN(D77,G77) -> 20000 | J77: =SUM(G77-I77)*H77+(G77-I77) -> 857564.39
A78: 100 | B78: 46160 | C78: Monday | D78: =Parâmetros!B5 -> 20000 | G78: =J77 -> 857564.39 | I78: =MIN(D78,G78) -> 20000 | J78: =SUM(G78-I78)*H78+(G78-I78) -> 837564.39
A79: 101 | B79: 46164 | C79: Friday | D79: =Parâmetros!B5 -> 20000 | G79: =J78 -> 837564.39 | I79: =MIN(D79,G79) -> 20000 | J79: =SUM(G79-I79)*H79+(G79-I79) -> 817564.39
A80: 102 | B80: 46167 | C80: Monday | D80: =Parâmetros!B5 -> 20000 | G80: =J79 -> 817564.39 | I80: =MIN(D80,G80) -> 20000 | J80: =SUM(G80-I80)*H80+(G80-I80) -> 797564.39
A81: 103 | B81: 46171 | C81: Friday | D81: =Parâmetros!B5 -> 20000 | G81: =J80 -> 797564.39 | H81: 0.017 | I81: =MIN(D81,G81) -> 20000 | J81: =SUM(G81-I81)*H81+(G81-I81) -> 790782.99
A82: 104 | B82: 46174 | C82: Monday | D82: =Parâmetros!B5 -> 20000 | G82: =J81 -> 790782.99 | I82: =MIN(D82,G82) -> 20000 | J82: =SUM(G82-I82)*H82+(G82-I82) -> 770782.99
A83: 105 | B83: 46178 | C83: Friday | D83: =Parâmetros!B5 -> 20000 | G83: =J82 -> 770782.99 | I83: =MIN(D83,G83) -> 20000 | J83: =SUM(G83-I83)*H83+(G83-I83) -> 750782.99
A84: 106 | B84: 46181 | C84: Monday | D84: =Parâmetros!B5 -> 20000 | G84: =J83 -> 750782.99 | I84: =MIN(D84,G84) -> 20000 | J84: =SUM(G84-I84)*H84+(G84-I84) -> 730782.99
A85: 107 | B85: 46185 | C85: Friday | D85: =Parâmetros!B5 -> 20000 | G85: =J84 -> 730782.99 | I85: =MIN(D85,G85) -> 20000 | J85: =SUM(G85-I85)*H85+(G85-I85) -> 710782.99
A86: 108 | B86: 46188 | C86: Monday | D86: =Parâmetros!B5 -> 20000 | G86: =J85 -> 710782.99 | I86: =MIN(D86,G86) -> 20000 | J86: =SUM(G86-I86)*H86+(G86-I86) -> 690782.99
A87: 109 | B87: 46192 | C87: Friday | D87: =Parâmetros!B5 -> 20000 | G87: =J86 -> 690782.99 | I87: =MIN(D87,G87) -> 20000 | J87: =SUM(G87-I87)*H87+(G87-I87) -> 670782.99
A88: 110 | B88: 46195 | C88: Monday | D88: =Parâmetros!B5 -> 20000 | G88: =J87 -> 670782.99 | I88: =MIN(D88,G88) -> 20000 | J88: =SUM(G88-I88)*H88+(G88-I88) -> 650782.99
A89: 111 | B89: 46199 | C89: Friday | D89: =Parâmetros!B5 -> 20000 | G89: =J88 -> 650782.99 | I89: =MIN(D89,G89) -> 20000 | J89: =SUM(G89-I89)*H89+(G89-I89) -> 630782.99
A90: 112 | B90: 46202 | C90: Monday | D90: =Parâmetros!B5 -> 20000 | G90: =J89 -> 630782.99 | H90: 0.0181 | I90: =MIN(D90,G90) -> 20000 | J90: =SUM(G90-I90)*H90+(G90-I90) -> 621838.16
A91: 113 | B91: 46206 | C91: Friday | D91: =Parâmetros!B5 -> 20000 | G91: =J90 -> 621838.16 | I91: =MIN(D91,G91) -> 20000 | J91: =SUM(G91-I91)*H91+(G91-I91) -> 601838.16
A92: 114 | B92: 46209 | C92: Monday | D92: =Parâmetros!B5 -> 20000 | G92: =J91 -> 601838.16 | I92: =MIN(D92,G92) -> 20000 | J92: =SUM(G92-I92)*H92+(G92-I92) -> 581838.16
A93: 115 | B93: 46213 | C93: Friday | D93: =Parâmetros!B5 -> 20000 | G93: =J92 -> 581838.16 | I93: =MIN(D93,G93) -> 20000 | J93: =SUM(G93-I93)*H93+(G93-I93) -> 561838.16
A94: 116 | B94: 46216 | C94: Monday | D94: =Parâmetros!B5 -> 20000 | G94: =J93 -> 561838.16 | I94: =MIN(D94,G94) -> 20000 | J94: =SUM(G94-I94)*H94+(G94-I94) -> 541838.16
A95: 117 | B95: 46220 | C95: Friday | D95: =Parâmetros!B5 -> 20000 | G95: =J94 -> 541838.16 | I95: =MIN(D95,G95) -> 20000 | J95: =SUM(G95-I95)*H95+(G95-I95) -> 521838.16
A96: 118 | B96: 46223 | C96: Monday | D96: =Parâmetros!B5 -> 20000 | G96: =J95 -> 521838.16 | I96: =MIN(D96,G96) -> 20000 | J96: =SUM(G96-I96)*H96+(G96-I96) -> 501838.16
A97: 119 | B97: 46227 | C97: Friday | D97: =Parâmetros!B5 -> 20000 | G97: =J96 -> 501838.16 | I97: =MIN(D97,G97) -> 20000 | J97: =SUM(G97-I97)*H97+(G97-I97) -> 481838.16
A98: 120 | B98: 46230 | C98: Monday | D98: =Parâmetros!B5 -> 20000 | G98: =J97 -> 481838.16 | I98: =MIN(D98,G98) -> 20000 | J98: =SUM(G98-I98)*H98+(G98-I98) -> 461838.16
A99: 121 | B99: 46234 | C99: Friday | D99: =Parâmetros!B5 -> 20000 | G99: =J98 -> 461838.16 | H99: 0.0176 | I99: =MIN(D99,G99) -> 20000 | J99: =SUM(G99-I99)*H99+(G99-I99) -> 449614.51
A100: 122 | B100: 46237 | C100: Monday | D100: =Parâmetros!B5 -> 20000 | G100: =J99 -> 449614.51 | I100: =MIN(D100,G100) -> 20000 | J100: =SUM(G100-I100)*H100+(G100-I100) -> 429614.51
A101: 123 | B101: 46241 | C101: Friday | D101: =Parâmetros!B5 -> 20000 | G101: =J100 -> 429614.51 | I101: =MIN(D101,G101) -> 20000 | J101: =SUM(G101-I101)*H101+(G101-I101) -> 409614.51
...
